{
  "a": {},
  "abbr": {},
  "abortable-fetch": {},
  "aborting": {
    "percentageOfPageLoad": 0.47365529,
    "chromeStatusUrl": "https://chromestatus.com/metrics/webfeature/timeline/popularity/124"
  },
  "abortsignal-any": {
    "percentageOfPageLoad": 0.00492532,
    "chromeStatusUrl": "https://chromestatus.com/metrics/webfeature/timeline/popularity/88"
  },
  "abs-sign": {},
  "absolute-positioning": {},
  "accelerometer": {
    "percentageOfPageLoad": 0.00214096,
    "chromeStatusUrl": "https://chromestatus.com/metrics/webfeature/timeline/popularity/147"
  },
  "accent-color": {
    "percentageOfPageLoad": 0.0236967,
    "chromeStatusUrl": "https://chromestatus.com/metrics/webfeature/timeline/popularity/6"
  },
  "accesskey": {},
  "accessor-methods": {},
  "active-view-transition": {
    "percentageOfPageLoad": 0.00095481,
    "chromeStatusUrl": "https://chromestatus.com/metrics/webfeature/timeline/popularity/217"
  },
  "address": {},
  "alerts": {},
  "align-content-block": {
    "percentageOfPageLoad": 0.07433899,
    "chromeStatusUrl": "https://chromestatus.com/metrics/webfeature/timeline/popularity/345"
  },
  "alignment-baseline": {},
  "all": {},
  "alt-text-generated-content": {},
  "alternative-style-sheets": {},
  "ambient-light": {},
  "anchor-positioning": {
    "percentageOfPageLoad": 0.00340859,
    "chromeStatusUrl": "https://chromestatus.com/metrics/webfeature/timeline/popularity/97"
  },
  "angle-instanced-arrays": {},
  "animation-composition": {
    "percentageOfPageLoad": 0.00373538,
    "chromeStatusUrl": "https://chromestatus.com/metrics/webfeature/timeline/popularity/7"
  },
  "animations-css": {},
  "app-file-handlers": {
    "percentageOfPageLoad": 6.6e-7,
    "chromeStatusUrl": "https://chromestatus.com/metrics/webfeature/timeline/popularity/299"
  },
  "app-launch-handler": {
    "percentageOfPageLoad": 0.00961718,
    "chromeStatusUrl": "https://chromestatus.com/metrics/webfeature/timeline/popularity/309"
  },
  "app-protocol-handlers": {
    "percentageOfPageLoad": 0.0041965,
    "chromeStatusUrl": "https://chromestatus.com/metrics/webfeature/timeline/popularity/300"
  },
  "app-share-targets": {
    "percentageOfPageLoad": 0.00275263,
    "chromeStatusUrl": "https://chromestatus.com/metrics/webfeature/timeline/popularity/304"
  },
  "app-shortcuts": {
    "percentageOfPageLoad": 0.01811372,
    "chromeStatusUrl": "https://chromestatus.com/metrics/webfeature/timeline/popularity/305"
  },
  "appearance": {
    "percentageOfPageLoad": 0.4682612,
    "chromeStatusUrl": "https://chromestatus.com/metrics/webfeature/timeline/popularity/8"
  },
  "arguments-callee": {},
  "aria-attribute-reflection": {
    "percentageOfPageLoad": 0.1646544,
    "chromeStatusUrl": "https://chromestatus.com/metrics/webfeature/timeline/popularity/96"
  },
  "array": {},
  "array-at": {},
  "array-by-copy": {
    "percentageOfPageLoad": 0.02492085,
    "chromeStatusUrl": "https://chromestatus.com/metrics/webfeature/timeline/popularity/223"
  },
  "array-copywithin": {},
  "array-fill": {},
  "array-find": {},
  "array-findlast": {
    "percentageOfPageLoad": 0.01437233,
    "chromeStatusUrl": "https://chromestatus.com/metrics/webfeature/timeline/popularity/238"
  },
  "array-flat": {},
  "array-from": {},
  "array-fromasync": {
    "percentageOfPageLoad": 0.01435209,
    "chromeStatusUrl": "https://chromestatus.com/metrics/webfeature/timeline/popularity/224"
  },
  "array-group": {
    "percentageOfPageLoad": 0.02755693,
    "chromeStatusUrl": "https://chromestatus.com/metrics/webfeature/timeline/popularity/239"
  },
  "array-includes": {},
  "array-isarray": {},
  "array-iteration-methods": {},
  "array-iterators": {},
  "array-of": {},
  "array-splice": {},
  "article": {},
  "aside": {},
  "aspect-ratio": {
    "percentageOfPageLoad": 0.32576338,
    "chromeStatusUrl": "https://chromestatus.com/metrics/webfeature/timeline/popularity/9"
  },
  "async-await": {},
  "async-clipboard": {
    "percentageOfPageLoad": 0.00403366,
    "chromeStatusUrl": "https://chromestatus.com/metrics/webfeature/timeline/popularity/121"
  },
  "async-generators": {},
  "async-iterable-streams": {
    "percentageOfPageLoad": 0.00226231,
    "chromeStatusUrl": "https://chromestatus.com/metrics/webfeature/timeline/popularity/279"
  },
  "async-iterators": {},
  "atomics-pause": {
    "percentageOfPageLoad": 7.7e-7,
    "chromeStatusUrl": "https://chromestatus.com/metrics/webfeature/timeline/popularity/377"
  },
  "atomics-wait-async": {
    "percentageOfPageLoad": 0.00010023,
    "chromeStatusUrl": "https://chromestatus.com/metrics/webfeature/timeline/popularity/242"
  },
  "attr": {},
  "attr-contents": {},
  "attribution-reporting": {
    "percentageOfPageLoad": 0.21772363,
    "chromeStatusUrl": "https://chromestatus.com/metrics/webfeature/timeline/popularity/282"
  },
  "audio": {},
  "audio-session": {},
  "audio-video-tracks": {},
  "audio-worklet": {
    "percentageOfPageLoad": 0.00149486,
    "chromeStatusUrl": "https://chromestatus.com/metrics/webfeature/timeline/popularity/152"
  },
  "autocapitalize": {},
  "autocorrect": {},
  "autofill": {
    "percentageOfPageLoad": 0.02454734,
    "chromeStatusUrl": "https://chromestatus.com/metrics/webfeature/timeline/popularity/352"
  },
  "autofocus": {},
  "autonomous-custom-elements": {},
  "avif": {
    "percentageOfPageLoad": 0.09074508,
    "chromeStatusUrl": "https://chromestatus.com/metrics/webfeature/timeline/popularity/10"
  },
  "b": {},
  "backdrop": {},
  "backdrop-filter": {
    "percentageOfPageLoad": 0.30634359,
    "chromeStatusUrl": "https://chromestatus.com/metrics/webfeature/timeline/popularity/11"
  },
  "background": {},
  "background-attachment": {},
  "background-blend-mode": {},
  "background-clip": {},
  "background-clip-border-area": {},
  "background-clip-text": {
    "percentageOfPageLoad": 0.43472185,
    "chromeStatusUrl": "https://chromestatus.com/metrics/webfeature/timeline/popularity/131"
  },
  "background-color": {},
  "background-fetch": {},
  "background-image": {},
  "background-origin": {},
  "background-position": {},
  "background-repeat": {},
  "background-size": {},
  "background-sync": {},
  "badging": {
    "percentageOfPageLoad": 0.00131036,
    "chromeStatusUrl": "https://chromestatus.com/metrics/webfeature/timeline/popularity/301"
  },
  "barcode": {},
  "barprop": {
    "percentageOfPageLoad": 0.13574044,
    "chromeStatusUrl": "https://chromestatus.com/metrics/webfeature/timeline/popularity/274"
  },
  "base": {},
  "base64encodedecode": {},
  "baseline-shift": {},
  "baseline-source": {
    "percentageOfPageLoad": 0.00023093,
    "chromeStatusUrl": "https://chromestatus.com/metrics/webfeature/timeline/popularity/214"
  },
  "battery": {},
  "bdi": {},
  "bdo": {},
  "beacons": {},
  "before-after": {},
  "beforeinstallprompt": {
    "percentageOfPageLoad": 0.1354264,
    "chromeStatusUrl": "https://chromestatus.com/metrics/webfeature/timeline/popularity/303"
  },
  "beforeunload": {
    "percentageOfPageLoad": 0.57248079,
    "chromeStatusUrl": "https://chromestatus.com/metrics/webfeature/timeline/popularity/275"
  },
  "bfcache-blocking-reasons": {
    "percentageOfPageLoad": 0.15310225,
    "chromeStatusUrl": "https://chromestatus.com/metrics/webfeature/timeline/popularity/276"
  },
  "bigint": {},
  "bigint64array": {},
  "blocking-render": {
    "percentageOfPageLoad": 0.10519319,
    "chromeStatusUrl": "https://chromestatus.com/metrics/webfeature/timeline/popularity/12"
  },
  "blockquote": {},
  "body": {},
  "border-image": {
    "percentageOfPageLoad": 0.05777276,
    "chromeStatusUrl": "https://chromestatus.com/metrics/webfeature/timeline/popularity/13"
  },
  "border-radius": {},
  "borders": {},
  "box-decoration-break": {
    "percentageOfPageLoad": 0.0267917,
    "chromeStatusUrl": "https://chromestatus.com/metrics/webfeature/timeline/popularity/218"
  },
  "box-shadow": {},
  "box-sizing": {},
  "br": {},
  "broadcast-channel": {
    "percentageOfPageLoad": 0.13846656,
    "chromeStatusUrl": "https://chromestatus.com/metrics/webfeature/timeline/popularity/14"
  },
  "brotli": {},
  "button": {},
  "calc": {},
  "calc-constants": {
    "percentageOfPageLoad": 0.00475453,
    "chromeStatusUrl": "https://chromestatus.com/metrics/webfeature/timeline/popularity/183"
  },
  "calc-size": {
    "percentageOfPageLoad": 0.0020385,
    "chromeStatusUrl": "https://chromestatus.com/metrics/webfeature/timeline/popularity/234"
  },
  "canvas": {
    "percentageOfPageLoad": 0.47439988,
    "chromeStatusUrl": "https://chromestatus.com/metrics/webfeature/timeline/popularity/200"
  },
  "canvas-2d": {
    "percentageOfPageLoad": 0.3328535,
    "chromeStatusUrl": "https://chromestatus.com/metrics/webfeature/timeline/popularity/201"
  },
  "canvas-2d-alpha": {
    "percentageOfPageLoad": 0.42981253,
    "chromeStatusUrl": "https://chromestatus.com/metrics/webfeature/timeline/popularity/202"
  },
  "canvas-2d-color-management": {
    "percentageOfPageLoad": 0.00006988,
    "chromeStatusUrl": "https://chromestatus.com/metrics/webfeature/timeline/popularity/203"
  },
  "canvas-2d-desynchronized": {
    "percentageOfPageLoad": 0.00306907,
    "chromeStatusUrl": "https://chromestatus.com/metrics/webfeature/timeline/popularity/204"
  },
  "canvas-2d-willreadfrequently": {
    "percentageOfPageLoad": 0.04659634,
    "chromeStatusUrl": "https://chromestatus.com/metrics/webfeature/timeline/popularity/205"
  },
  "canvas-2dalpha": {
    "percentageOfPageLoad": 0.33218082,
    "chromeStatusUrl": "https://chromestatus.com/metrics/webfeature/timeline/popularity/202"
  },
  "canvas-2dcolor-management": {
    "percentageOfPageLoad": 0.00039463,
    "chromeStatusUrl": "https://chromestatus.com/metrics/webfeature/timeline/popularity/203"
  },
  "canvas-2ddesynchronized": {
    "percentageOfPageLoad": 0.00268321,
    "chromeStatusUrl": "https://chromestatus.com/metrics/webfeature/timeline/popularity/204"
  },
  "canvas-2dwillreadfrequently": {
    "percentageOfPageLoad": 0.04043876,
    "chromeStatusUrl": "https://chromestatus.com/metrics/webfeature/timeline/popularity/205"
  },
  "canvas-context-lost": {
    "percentageOfPageLoad": 0.00084381,
    "chromeStatusUrl": "https://chromestatus.com/metrics/webfeature/timeline/popularity/15"
  },
  "canvas-createconicgradient": {
    "percentageOfPageLoad": 0.00005161,
    "chromeStatusUrl": "https://chromestatus.com/metrics/webfeature/timeline/popularity/91"
  },
  "canvas-reset": {
    "percentageOfPageLoad": 0.00012312,
    "chromeStatusUrl": "https://chromestatus.com/metrics/webfeature/timeline/popularity/92"
  },
  "canvas-roundrect": {
    "percentageOfPageLoad": 0.00103592,
    "chromeStatusUrl": "https://chromestatus.com/metrics/webfeature/timeline/popularity/93"
  },
  "cap": {
    "percentageOfPageLoad": 0.00015669,
    "chromeStatusUrl": "https://chromestatus.com/metrics/webfeature/timeline/popularity/157"
  },
  "capture-stream-audio-video": {},
  "capture-stream-canvas": {},
  "caret-color": {},
  "cascade-layers": {
    "percentageOfPageLoad": 0.04084928,
    "chromeStatusUrl": "https://chromestatus.com/metrics/webfeature/timeline/popularity/5"
  },
  "case-insensitive-attributes": {},
  "case-sensitive-attributes": {},
  "ch": {
    "percentageOfPageLoad": 0.04667452,
    "chromeStatusUrl": "https://chromestatus.com/metrics/webfeature/timeline/popularity/206"
  },
  "change-event": {},
  "channel-messaging": {},
  "charset": {},
  "check-visibility": {
    "percentageOfPageLoad": 0.03245271,
    "chromeStatusUrl": "https://chromestatus.com/metrics/webfeature/timeline/popularity/133"
  },
  "cite": {},
  "class-syntax": {},
  "clear-site-data": {
    "percentageOfPageLoad": 0.00298333,
    "chromeStatusUrl": "https://chromestatus.com/metrics/webfeature/timeline/popularity/339"
  },
  "clip": {},
  "clip-path": {
    "percentageOfPageLoad": 0.41814202,
    "chromeStatusUrl": "https://chromestatus.com/metrics/webfeature/timeline/popularity/216"
  },
  "clip-path-animatable": {},
  "clip-path-boxes": {
    "percentageOfPageLoad": 0.00075384,
    "chromeStatusUrl": "https://chromestatus.com/metrics/webfeature/timeline/popularity/215"
  },
  "clipboard-custom-format": {
    "percentageOfPageLoad": 0.00002524,
    "chromeStatusUrl": "https://chromestatus.com/metrics/webfeature/timeline/popularity/271"
  },
  "clipboard-events": {},
  "clipboard-supports": {
    "percentageOfPageLoad": 0.00165745,
    "chromeStatusUrl": "https://chromestatus.com/metrics/webfeature/timeline/popularity/273"
  },
  "clipboard-svg": {
    "percentageOfPageLoad": 0.00000171,
    "chromeStatusUrl": "https://chromestatus.com/metrics/webfeature/timeline/popularity/272"
  },
  "clipboard-unsanitized-formats": {
    "percentageOfPageLoad": 0.00003309,
    "chromeStatusUrl": "https://chromestatus.com/metrics/webfeature/timeline/popularity/123"
  },
  "closewatcher": {
    "percentageOfPageLoad": 0.00014179,
    "chromeStatusUrl": "https://chromestatus.com/metrics/webfeature/timeline/popularity/259"
  },
  "code": {},
  "color": {},
  "color-adjust": {},
  "color-contrast": {},
  "color-function": {
    "percentageOfPageLoad": 0.00980004,
    "chromeStatusUrl": "https://chromestatus.com/metrics/webfeature/timeline/popularity/169"
  },
  "color-gamut": {},
  "color-mix": {
    "percentageOfPageLoad": 0.07827064,
    "chromeStatusUrl": "https://chromestatus.com/metrics/webfeature/timeline/popularity/95"
  },
  "color-scheme": {
    "percentageOfPageLoad": 0.16992454,
    "chromeStatusUrl": "https://chromestatus.com/metrics/webfeature/timeline/popularity/16"
  },
  "colrv0": {},
  "colrv1": {},
  "column-breaks": {},
  "column-fill": {},
  "column-pseudo": {
    "percentageOfPageLoad": 1.6e-7,
    "chromeStatusUrl": "https://chromestatus.com/metrics/webfeature/timeline/popularity/292"
  },
  "column-span": {},
  "composed-ranges": {
    "percentageOfPageLoad": 0.00006321,
    "chromeStatusUrl": "https://chromestatus.com/metrics/webfeature/timeline/popularity/314"
  },
  "composition-events": {},
  "compression-dictionary-transport": {
    "percentageOfPageLoad": 0.0878202,
    "chromeStatusUrl": "https://chromestatus.com/metrics/webfeature/timeline/popularity/315"
  },
  "compression-streams": {
    "percentageOfPageLoad": 0.22789809,
    "chromeStatusUrl": "https://chromestatus.com/metrics/webfeature/timeline/popularity/1"
  },
  "compute-pressure": {
    "percentageOfPageLoad": 0.00235262,
    "chromeStatusUrl": "https://chromestatus.com/metrics/webfeature/timeline/popularity/17"
  },
  "conic-gradients": {},
  "console": {},
  "constraint-validation": {},
  "constructed-stylesheets": {
    "percentageOfPageLoad": 0.10021798,
    "chromeStatusUrl": "https://chromestatus.com/metrics/webfeature/timeline/popularity/18"
  },
  "contact-picker": {},
  "contain": {},
  "contain-inline-size": {
    "percentageOfPageLoad": 0.00038936,
    "chromeStatusUrl": "https://chromestatus.com/metrics/webfeature/timeline/popularity/132"
  },
  "contain-intrinsic-size": {
    "percentageOfPageLoad": 0.07452738,
    "chromeStatusUrl": "https://chromestatus.com/metrics/webfeature/timeline/popularity/21"
  },
  "contain-layout": {},
  "contain-paint": {},
  "contain-size": {},
  "contain-style": {},
  "container-queries": {
    "percentageOfPageLoad": 0.15815771,
    "chromeStatusUrl": "https://chromestatus.com/metrics/webfeature/timeline/popularity/19"
  },
  "container-scroll-state-queries": {
    "percentageOfPageLoad": 0.00399236,
    "chromeStatusUrl": "https://chromestatus.com/metrics/webfeature/timeline/popularity/280"
  },
  "container-style-queries": {
    "percentageOfPageLoad": 0.00560758,
    "chromeStatusUrl": "https://chromestatus.com/metrics/webfeature/timeline/popularity/20"
  },
  "content": {},
  "content-index": {},
  "content-visibility": {
    "percentageOfPageLoad": 0.08138937,
    "chromeStatusUrl": "https://chromestatus.com/metrics/webfeature/timeline/popularity/148"
  },
  "contenteditable": {},
  "contenteditable-plaintextonly": {},
  "context-fill-stroke": {
    "percentageOfPageLoad": 0.00005701,
    "chromeStatusUrl": "https://chromestatus.com/metrics/webfeature/timeline/popularity/155"
  },
  "contrast-color": {},
  "controls-list": {},
  "cookie-enabled": {},
  "cookie-store": {
    "percentageOfPageLoad": 0.09167472,
    "chromeStatusUrl": "https://chromestatus.com/metrics/webfeature/timeline/popularity/283"
  },
  "cookies": {},
  "corner-shape": {},
  "cors": {},
  "counter-reset-reversed": {},
  "counter-set": {
    "percentageOfPageLoad": 0.00533063,
    "chromeStatusUrl": "https://chromestatus.com/metrics/webfeature/timeline/popularity/149"
  },
  "counter-style": {
    "percentageOfPageLoad": 0.00337096,
    "chromeStatusUrl": "https://chromestatus.com/metrics/webfeature/timeline/popularity/22"
  },
  "counters": {},
  "createimagebitmap": {},
  "credential-management": {},
  "crisp-edges": {},
  "cross-document-view-transitions": {
    "percentageOfPageLoad": 0.10968227,
    "chromeStatusUrl": "https://chromestatus.com/metrics/webfeature/timeline/popularity/232"
  },
  "cross-fade": {},
  "csp": {},
  "css-escape": {},
  "css-modules": {
    "percentageOfPageLoad": 5.7e-7,
    "chromeStatusUrl": "https://chromestatus.com/metrics/webfeature/timeline/popularity/23"
  },
  "css-object-model": {},
  "css-object-model-discouraged": {},
  "css-supports": {},
  "css-typed-om": {},
  "cubic-bezier-easing": {},
  "currentcolor": {},
  "cursor": {},
  "custom-ellipses": {},
  "custom-properties": {},
  "customizable-select": {
    "percentageOfPageLoad": 0.00014068,
    "chromeStatusUrl": "https://chromestatus.com/metrics/webfeature/timeline/popularity/342"
  },
  "customized-built-in-elements": {},
  "data": {},
  "data-urls": {},
  "datalist": {
    "percentageOfPageLoad": 0.02121264,
    "chromeStatusUrl": "https://chromestatus.com/metrics/webfeature/timeline/popularity/84"
  },
  "dataset": {},
  "date": {},
  "date-get-year-set-year": {},
  "date-to-gmt-string": {},
  "declarative-shadow-dom": {
    "percentageOfPageLoad": 0.00265161,
    "chromeStatusUrl": "https://chromestatus.com/metrics/webfeature/timeline/popularity/24"
  },
  "dedicated-workers": {},
  "default": {},
  "del": {},
  "description-list": {},
  "destructuring": {},
  "details": {},
  "details-content": {
    "percentageOfPageLoad": 0.00688158,
    "chromeStatusUrl": "https://chromestatus.com/metrics/webfeature/timeline/popularity/354"
  },
  "details-name": {
    "percentageOfPageLoad": 0.00051469,
    "chromeStatusUrl": "https://chromestatus.com/metrics/webfeature/timeline/popularity/114"
  },
  "device-memory": {},
  "device-orientation-events": {
    "percentageOfPageLoad": 0.06355176,
    "chromeStatusUrl": "https://chromestatus.com/metrics/webfeature/timeline/popularity/102"
  },
  "device-posture": {
    "percentageOfPageLoad": 0.01013858,
    "chromeStatusUrl": "https://chromestatus.com/metrics/webfeature/timeline/popularity/401"
  },
  "device-queries": {},
  "devicepixelratio": {},
  "dfn": {},
  "dialog": {
    "percentageOfPageLoad": 0.0821877,
    "chromeStatusUrl": "https://chromestatus.com/metrics/webfeature/timeline/popularity/25"
  },
  "dialog-closedby": {
    "percentageOfPageLoad": 0.0003595,
    "chromeStatusUrl": "https://chromestatus.com/metrics/webfeature/timeline/popularity/350"
  },
  "digital-goods": {},
  "dir-pseudo": {
    "percentageOfPageLoad": 0.06958502,
    "chromeStatusUrl": "https://chromestatus.com/metrics/webfeature/timeline/popularity/85"
  },
  "dirname": {},
  "display": {},
  "display-animation": {
    "percentageOfPageLoad": 0.03025253,
    "chromeStatusUrl": "https://chromestatus.com/metrics/webfeature/timeline/popularity/233"
  },
  "display-contents": {},
  "display-flow-root": {},
  "display-list-item": {},
  "display-mode": {
    "percentageOfPageLoad": 0.15538476,
    "chromeStatusUrl": "https://chromestatus.com/metrics/webfeature/timeline/popularity/199"
  },
  "display-ruby": {},
  "display-table": {},
  "div": {},
  "document-caretpositionfrompoint": {
    "percentageOfPageLoad": 0.05164086,
    "chromeStatusUrl": "https://chromestatus.com/metrics/webfeature/timeline/popularity/144"
  },
  "document-colors": {},
  "document-picture-in-picture": {
    "percentageOfPageLoad": 0.00038935,
    "chromeStatusUrl": "https://chromestatus.com/metrics/webfeature/timeline/popularity/26"
  },
  "document-write": {},
  "dom": {},
  "dom-geometry": {},
  "dominant-baseline": {},
  "domparser": {},
  "download": {},
  "draganddrop": {},
  "dynamic-range": {
    "percentageOfPageLoad": 0.04502056,
    "chromeStatusUrl": "https://chromestatus.com/metrics/webfeature/timeline/popularity/198"
  },
  "early-data": {},
  "edit-context": {
    "percentageOfPageLoad": 0.02225256,
    "chromeStatusUrl": "https://chromestatus.com/metrics/webfeature/timeline/popularity/125"
  },
  "element": {},
  "element-capture": {
    "percentageOfPageLoad": 1.9e-7,
    "chromeStatusUrl": "https://chromestatus.com/metrics/webfeature/timeline/popularity/321"
  },
  "element-from-point": {},
  "element-timing": {},
  "em": {},
  "em-unit": {},
  "embed": {},
  "empty": {},
  "encrypted-media-extensions": {},
  "enterkeyhint": {},
  "error-cause": {},
  "escape-unescape": {},
  "event-timing": {},
  "events": {},
  "ex": {},
  "execcommand": {},
  "exp-functions": {
    "percentageOfPageLoad": 0.00035268,
    "chromeStatusUrl": "https://chromestatus.com/metrics/webfeature/timeline/popularity/184"
  },
  "explicit-resource-management": {
    "percentageOfPageLoad": 0.00239743,
    "chromeStatusUrl": "https://chromestatus.com/metrics/webfeature/timeline/popularity/308"
  },
  "exponentiation": {},
  "ext-blend-minmax": {},
  "ext-color-buffer-float": {},
  "ext-color-buffer-half-float": {},
  "ext-disjoint-timer-query": {},
  "ext-float-blend": {},
  "ext-frag-depth": {},
  "ext-shader-texture-lod": {},
  "ext-srgb": {},
  "ext-texture-compression-bptc": {
    "percentageOfPageLoad": 0.00923202,
    "chromeStatusUrl": "https://chromestatus.com/metrics/webfeature/timeline/popularity/381"
  },
  "ext-texture-compression-rgtc": {
    "percentageOfPageLoad": 0.00900858,
    "chromeStatusUrl": "https://chromestatus.com/metrics/webfeature/timeline/popularity/382"
  },
  "ext-texture-filter-anisotropic": {},
  "ext-texture-norm-16": {
    "percentageOfPageLoad": 0.00224323,
    "chromeStatusUrl": "https://chromestatus.com/metrics/webfeature/timeline/popularity/383"
  },
  "ext-texture-norm16": {},
  "external": {},
  "eyedropper": {
    "percentageOfPageLoad": 0.00002755,
    "chromeStatusUrl": "https://chromestatus.com/metrics/webfeature/timeline/popularity/130"
  },
  "fast-seek": {},
  "fedcm": {
    "percentageOfPageLoad": 0.02263923,
    "chromeStatusUrl": "https://chromestatus.com/metrics/webfeature/timeline/popularity/247"
  },
  "federated-credentials": {},
  "fencedframe": {
    "percentageOfPageLoad": 0.00546527,
    "chromeStatusUrl": "https://chromestatus.com/metrics/webfeature/timeline/popularity/284"
  },
  "fetch": {},
  "fetch-metadata": {},
  "fetch-priority": {
    "percentageOfPageLoad": 0.36914639,
    "chromeStatusUrl": "https://chromestatus.com/metrics/webfeature/timeline/popularity/268"
  },
  "fetch-request-streams": {
    "percentageOfPageLoad": 0.0000121,
    "chromeStatusUrl": "https://chromestatus.com/metrics/webfeature/timeline/popularity/398"
  },
  "fetchlater": {
    "percentageOfPageLoad": 0.0367572,
    "chromeStatusUrl": "https://chromestatus.com/metrics/webfeature/timeline/popularity/306"
  },
  "field-sizing": {
    "percentageOfPageLoad": 0.01427481,
    "chromeStatusUrl": "https://chromestatus.com/metrics/webfeature/timeline/popularity/113"
  },
  "fieldset": {},
  "figure": {},
  "file": {},
  "file-selector-button": {
    "percentageOfPageLoad": 0.07432135,
    "chromeStatusUrl": "https://chromestatus.com/metrics/webfeature/timeline/popularity/185"
  },
  "file-system-access": {
    "percentageOfPageLoad": 0.00004692,
    "chromeStatusUrl": "https://chromestatus.com/metrics/webfeature/timeline/popularity/258"
  },
  "filter": {},
  "first-letter": {},
  "first-line": {},
  "fit-content": {},
  "fit-content-function": {},
  "fixed-positioning": {},
  "flexbox": {
    "percentageOfPageLoad": 0.82786068,
    "chromeStatusUrl": "https://chromestatus.com/metrics/webfeature/timeline/popularity/28"
  },
  "flexbox-gap": {
    "percentageOfPageLoad": 0.565651,
    "chromeStatusUrl": "https://chromestatus.com/metrics/webfeature/timeline/popularity/27"
  },
  "float-16array": {
    "percentageOfPageLoad": 0.02271694,
    "chromeStatusUrl": "https://chromestatus.com/metrics/webfeature/timeline/popularity/298"
  },
  "float-clear": {},
  "float16array": {
    "percentageOfPageLoad": 0.0098443,
    "chromeStatusUrl": "https://chromestatus.com/metrics/webfeature/timeline/popularity/298"
  },
  "focus-events": {},
  "focus-visible": {
    "percentageOfPageLoad": 0.53357182,
    "chromeStatusUrl": "https://chromestatus.com/metrics/webfeature/timeline/popularity/29"
  },
  "focus-within": {},
  "font-display": {},
  "font-face": {},
  "font-family": {},
  "font-family-math": {
    "percentageOfPageLoad": 0.00054381,
    "chromeStatusUrl": "https://chromestatus.com/metrics/webfeature/timeline/popularity/351"
  },
  "font-family-system": {},
  "font-family-ui": {},
  "font-feature-settings": {},
  "font-kerning": {},
  "font-language-override": {
    "percentageOfPageLoad": 0.00428571,
    "chromeStatusUrl": "https://chromestatus.com/metrics/webfeature/timeline/popularity/411"
  },
  "font-loading": {},
  "font-metric-overrides": {
    "percentageOfPageLoad": 0.08845375,
    "chromeStatusUrl": "https://chromestatus.com/metrics/webfeature/timeline/popularity/353"
  },
  "font-optical-sizing": {
    "percentageOfPageLoad": 0.02599802,
    "chromeStatusUrl": "https://chromestatus.com/metrics/webfeature/timeline/popularity/30"
  },
  "font-palette": {
    "percentageOfPageLoad": 0.00049869,
    "chromeStatusUrl": "https://chromestatus.com/metrics/webfeature/timeline/popularity/32"
  },
  "font-palette-animation": {
    "percentageOfPageLoad": 9.6e-7,
    "chromeStatusUrl": "https://chromestatus.com/metrics/webfeature/timeline/popularity/31"
  },
  "font-shorthand": {},
  "font-size": {},
  "font-size-adjust": {
    "percentageOfPageLoad": 0.01754811,
    "chromeStatusUrl": "https://chromestatus.com/metrics/webfeature/timeline/popularity/220"
  },
  "font-stretch": {},
  "font-style": {},
  "font-synthesis": {
    "percentageOfPageLoad": 0.0168066,
    "chromeStatusUrl": "https://chromestatus.com/metrics/webfeature/timeline/popularity/36"
  },
  "font-synthesis-position": {},
  "font-synthesis-small-caps": {
    "percentageOfPageLoad": 0.00014288,
    "chromeStatusUrl": "https://chromestatus.com/metrics/webfeature/timeline/popularity/33"
  },
  "font-synthesis-style": {
    "percentageOfPageLoad": 0.00035149,
    "chromeStatusUrl": "https://chromestatus.com/metrics/webfeature/timeline/popularity/34"
  },
  "font-synthesis-weight": {
    "percentageOfPageLoad": 0.00115623,
    "chromeStatusUrl": "https://chromestatus.com/metrics/webfeature/timeline/popularity/35"
  },
  "font-variant": {},
  "font-variant-alternates": {
    "percentageOfPageLoad": 0.00353574,
    "chromeStatusUrl": "https://chromestatus.com/metrics/webfeature/timeline/popularity/37"
  },
  "font-variant-caps": {},
  "font-variant-east-asian": {},
  "font-variant-emoji": {
    "percentageOfPageLoad": 0.00061351,
    "chromeStatusUrl": "https://chromestatus.com/metrics/webfeature/timeline/popularity/285"
  },
  "font-variant-ligatures": {},
  "font-variant-numeric": {},
  "font-variant-position": {
    "percentageOfPageLoad": 0.00298657,
    "chromeStatusUrl": "https://chromestatus.com/metrics/webfeature/timeline/popularity/179"
  },
  "font-variation-settings": {},
  "font-weight": {},
  "font-width": {},
  "forced-colors": {
    "percentageOfPageLoad": 0.33265385,
    "chromeStatusUrl": "https://chromestatus.com/metrics/webfeature/timeline/popularity/165"
  },
  "form": {},
  "form-associated-custom-elements": {},
  "form-validity-pseudos": {},
  "fullscreen": {},
  "function": {
    "percentageOfPageLoad": 0.00002602,
    "chromeStatusUrl": "https://chromestatus.com/metrics/webfeature/timeline/popularity/310"
  },
  "functions": {},
  "functions-caller-arguments": {},
  "gamepad": {
    "percentageOfPageLoad": 0.00001052,
    "chromeStatusUrl": "https://chromestatus.com/metrics/webfeature/timeline/popularity/103"
  },
  "gamepad-haptics": {},
  "gamepad-touch": {},
  "gamepad-vr": {},
  "gap-decorations": {},
  "generators": {},
  "geolocation": {},
  "get-computed-style": {},
  "getboxquads": {},
  "gethtml": {
    "percentageOfPageLoad": 0.00130008,
    "chromeStatusUrl": "https://chromestatus.com/metrics/webfeature/timeline/popularity/286"
  },
  "globalthis": {},
  "glyph-orientation-vertical": {},
  "gpc": {},
  "gradient-interpolation": {
    "percentageOfPageLoad": 0.01387424,
    "chromeStatusUrl": "https://chromestatus.com/metrics/webfeature/timeline/popularity/178"
  },
  "gradients": {},
  "grid": {
    "percentageOfPageLoad": 0.40210699,
    "chromeStatusUrl": "https://chromestatus.com/metrics/webfeature/timeline/popularity/38"
  },
  "grid-animation": {},
  "gyroscope": {},
  "hanging-punctuation": {},
  "hardware-concurrency": {},
  "has": {
    "percentageOfPageLoad": 0.46452004,
    "chromeStatusUrl": "https://chromestatus.com/metrics/webfeature/timeline/popularity/39"
  },
  "has-slotted": {
    "percentageOfPageLoad": 2e-8,
    "chromeStatusUrl": "https://chromestatus.com/metrics/webfeature/timeline/popularity/320"
  },
  "hashbang-comments": {},
  "hashchange": {},
  "head": {},
  "header-footer": {},
  "heading-selectors": {},
  "headings": {},
  "hgroup": {},
  "hidden-until-found": {
    "percentageOfPageLoad": 0.00162481,
    "chromeStatusUrl": "https://chromestatus.com/metrics/webfeature/timeline/popularity/86"
  },
  "highlight": {
    "percentageOfPageLoad": 0.0004762,
    "chromeStatusUrl": "https://chromestatus.com/metrics/webfeature/timeline/popularity/269"
  },
  "history": {},
  "host": {},
  "host-context": {},
  "hr": {},
  "hsl": {},
  "hsts": {},
  "html": {},
  "html-media-capture": {},
  "html-wrapper-methods": {
    "percentageOfPageLoad": 0.08205347,
    "chromeStatusUrl": "https://chromestatus.com/metrics/webfeature/timeline/popularity/394"
  },
  "http-3": {
    "percentageOfPageLoad": 0.46663921,
    "chromeStatusUrl": "https://chromestatus.com/metrics/webfeature/timeline/popularity/316"
  },
  "http-authentication": {},
  "http11": {},
  "http2": {},
  "http3": {},
  "hwb": {
    "percentageOfPageLoad": 0.00213415,
    "chromeStatusUrl": "https://chromestatus.com/metrics/webfeature/timeline/popularity/172"
  },
  "hyphenate-character": {
    "percentageOfPageLoad": 0.00287014,
    "chromeStatusUrl": "https://chromestatus.com/metrics/webfeature/timeline/popularity/211"
  },
  "hyphenate-limit-chars": {
    "percentageOfPageLoad": 0.00121031,
    "chromeStatusUrl": "https://chromestatus.com/metrics/webfeature/timeline/popularity/212"
  },
  "hyphens": {
    "percentageOfPageLoad": 0.10278232,
    "chromeStatusUrl": "https://chromestatus.com/metrics/webfeature/timeline/popularity/40"
  },
  "i": {},
  "ic": {
    "percentageOfPageLoad": 0.00000219,
    "chromeStatusUrl": "https://chromestatus.com/metrics/webfeature/timeline/popularity/159"
  },
  "idle-detection": {
    "percentageOfPageLoad": 0.00029595,
    "chromeStatusUrl": "https://chromestatus.com/metrics/webfeature/timeline/popularity/41"
  },
  "if": {
    "percentageOfPageLoad": 0.00143518,
    "chromeStatusUrl": "https://chromestatus.com/metrics/webfeature/timeline/popularity/311"
  },
  "iframe": {},
  "iframe-credentialless": {
    "percentageOfPageLoad": 0.00064282,
    "chromeStatusUrl": "https://chromestatus.com/metrics/webfeature/timeline/popularity/325"
  },
  "iframe-sandbox": {},
  "iframe-srcdoc": {},
  "image-function": {},
  "image-maps": {},
  "image-orientation": {
    "percentageOfPageLoad": 0.00274715,
    "chromeStatusUrl": "https://chromestatus.com/metrics/webfeature/timeline/popularity/167"
  },
  "image-rendering": {},
  "image-set": {
    "percentageOfPageLoad": 0.00449139,
    "chromeStatusUrl": "https://chromestatus.com/metrics/webfeature/timeline/popularity/98"
  },
  "imagebitmaprenderingcontext": {},
  "ime-mode": {},
  "img": {},
  "import": {},
  "import-assertions": {},
  "import-maps": {
    "percentageOfPageLoad": 0.00721635,
    "chromeStatusUrl": "https://chromestatus.com/metrics/webfeature/timeline/popularity/42"
  },
  "indeterminate": {},
  "indexeddb": {},
  "individual-transforms": {
    "percentageOfPageLoad": 0.18924954,
    "chromeStatusUrl": "https://chromestatus.com/metrics/webfeature/timeline/popularity/43"
  },
  "inert": {
    "percentageOfPageLoad": 0.0270511,
    "chromeStatusUrl": "https://chromestatus.com/metrics/webfeature/timeline/popularity/128"
  },
  "inherit-value": {},
  "initial-letter": {
    "percentageOfPageLoad": 0.0008223,
    "chromeStatusUrl": "https://chromestatus.com/metrics/webfeature/timeline/popularity/210"
  },
  "initial-value": {},
  "ink": {
    "percentageOfPageLoad": 0.00008605,
    "chromeStatusUrl": "https://chromestatus.com/metrics/webfeature/timeline/popularity/263"
  },
  "input": {},
  "input-button": {},
  "input-checkbox": {},
  "input-color": {},
  "input-date-time": {},
  "input-email-tel-url": {},
  "input-event": {},
  "input-file": {},
  "input-hidden": {},
  "input-image": {},
  "input-number": {},
  "input-password": {},
  "input-radio": {},
  "input-range": {},
  "input-reset": {},
  "input-selectors": {},
  "input-submit": {},
  "inputmode": {},
  "ins": {},
  "insertable-streams": {},
  "interaction": {},
  "interactivity": {
    "percentageOfPageLoad": 0.00027499,
    "chromeStatusUrl": "https://chromestatus.com/metrics/webfeature/timeline/popularity/293"
  },
  "interpolate-size": {
    "percentageOfPageLoad": 0.03132542,
    "chromeStatusUrl": "https://chromestatus.com/metrics/webfeature/timeline/popularity/235"
  },
  "intersection-observer": {
    "percentageOfPageLoad": 0.53887834,
    "chromeStatusUrl": "https://chromestatus.com/metrics/webfeature/timeline/popularity/45"
  },
  "intersection-observer-v2": {
    "percentageOfPageLoad": 0.08938952,
    "chromeStatusUrl": "https://chromestatus.com/metrics/webfeature/timeline/popularity/44"
  },
  "intl": {},
  "intl-display-names": {
    "percentageOfPageLoad": 0.01902341,
    "chromeStatusUrl": "https://chromestatus.com/metrics/webfeature/timeline/popularity/328"
  },
  "intl-duration-format": {
    "percentageOfPageLoad": 0.00008182,
    "chromeStatusUrl": "https://chromestatus.com/metrics/webfeature/timeline/popularity/266"
  },
  "intl-list-format": {},
  "intl-locale": {},
  "intl-locale-info": {
    "percentageOfPageLoad": 0.01628398,
    "chromeStatusUrl": "https://chromestatus.com/metrics/webfeature/timeline/popularity/244"
  },
  "intl-plural-rules": {},
  "intl-relative-time-format": {},
  "intl-segmenter": {
    "percentageOfPageLoad": 0.02143505,
    "chromeStatusUrl": "https://chromestatus.com/metrics/webfeature/timeline/popularity/129"
  },
  "inverted-colors": {},
  "invoker-commands": {},
  "is": {
    "percentageOfPageLoad": 0.29017495,
    "chromeStatusUrl": "https://chromestatus.com/metrics/webfeature/timeline/popularity/46"
  },
  "is-error": {
    "percentageOfPageLoad": 0.01480655,
    "chromeStatusUrl": "https://chromestatus.com/metrics/webfeature/timeline/popularity/270"
  },
  "is-input-pending": {},
  "is-secure-context": {},
  "isolation": {},
  "iterator-methods": {
    "percentageOfPageLoad": 0.04078167,
    "chromeStatusUrl": "https://chromestatus.com/metrics/webfeature/timeline/popularity/225"
  },
  "iterators": {},
  "javascript": {},
  "jpegxl": {
    "percentageOfPageLoad": 6e-8,
    "chromeStatusUrl": "https://chromestatus.com/metrics/webfeature/timeline/popularity/418"
  },
  "js-modules": {
    "percentageOfPageLoad": 0.30012931,
    "chromeStatusUrl": "https://chromestatus.com/metrics/webfeature/timeline/popularity/47"
  },
  "js-modules-service-workers": {},
  "js-modules-shared-workers": {
    "percentageOfPageLoad": 0.00722215,
    "chromeStatusUrl": "https://chromestatus.com/metrics/webfeature/timeline/popularity/109"
  },
  "js-modules-workers": {
    "percentageOfPageLoad": 0.0057382,
    "chromeStatusUrl": "https://chromestatus.com/metrics/webfeature/timeline/popularity/110"
  },
  "json": {},
  "json-modules": {
    "percentageOfPageLoad": 0.00001533,
    "chromeStatusUrl": "https://chromestatus.com/metrics/webfeature/timeline/popularity/396"
  },
  "json-raw": {},
  "kbd": {},
  "keyboard-events": {},
  "keyboard-lock": {
    "percentageOfPageLoad": 0.00007238,
    "chromeStatusUrl": "https://chromestatus.com/metrics/webfeature/timeline/popularity/119"
  },
  "keyboard-map": {
    "percentageOfPageLoad": 0.0800064,
    "chromeStatusUrl": "https://chromestatus.com/metrics/webfeature/timeline/popularity/116"
  },
  "khr-parallel-shader-compile": {},
  "lab": {
    "percentageOfPageLoad": 0.00913197,
    "chromeStatusUrl": "https://chromestatus.com/metrics/webfeature/timeline/popularity/171"
  },
  "label": {},
  "lang": {},
  "lang-attr": {},
  "language": {},
  "language-detector": {
    "percentageOfPageLoad": 0.016588,
    "chromeStatusUrl": "https://chromestatus.com/metrics/webfeature/timeline/popularity/425"
  },
  "largest-contentful-paint": {},
  "layout-direction-override": {},
  "layout-instability": {
    "percentageOfPageLoad": 0.41652321,
    "chromeStatusUrl": "https://chromestatus.com/metrics/webfeature/timeline/popularity/277"
  },
  "let-const": {},
  "letter-spacing": {},
  "lh": {
    "percentageOfPageLoad": 0.00979614,
    "chromeStatusUrl": "https://chromestatus.com/metrics/webfeature/timeline/popularity/161"
  },
  "light-dark": {
    "percentageOfPageLoad": 0.01173149,
    "chromeStatusUrl": "https://chromestatus.com/metrics/webfeature/timeline/popularity/337"
  },
  "line-break": {
    "percentageOfPageLoad": 0.05228978,
    "chromeStatusUrl": "https://chromestatus.com/metrics/webfeature/timeline/popularity/335"
  },
  "line-clamp": {},
  "line-height": {},
  "linear-easing": {
    "percentageOfPageLoad": 0.12779039,
    "chromeStatusUrl": "https://chromestatus.com/metrics/webfeature/timeline/popularity/186"
  },
  "link": {},
  "link-rel-dns-prefetch": {},
  "link-rel-expect": {
    "percentageOfPageLoad": 0.10411967,
    "chromeStatusUrl": "https://chromestatus.com/metrics/webfeature/timeline/popularity/340"
  },
  "link-rel-preconnect": {},
  "link-rel-prefetch": {},
  "link-rel-preload": {},
  "link-selectors": {},
  "list-elements": {},
  "list-style": {},
  "loading-lazy": {},
  "local-fonts": {
    "percentageOfPageLoad": 0.00001099,
    "chromeStatusUrl": "https://chromestatus.com/metrics/webfeature/timeline/popularity/287"
  },
  "local-network-access": {},
  "localstorage": {},
  "location": {},
  "logical-assignments": {
    "percentageOfPageLoad": 0.21169813,
    "chromeStatusUrl": "https://chromestatus.com/metrics/webfeature/timeline/popularity/378"
  },
  "logical-properties": {
    "percentageOfPageLoad": 0.33653347,
    "chromeStatusUrl": "https://chromestatus.com/metrics/webfeature/timeline/popularity/168"
  },
  "long-animation-frames": {
    "percentageOfPageLoad": 0.14647954,
    "chromeStatusUrl": "https://chromestatus.com/metrics/webfeature/timeline/popularity/236"
  },
  "longtasks": {},
  "magnetometer": {},
  "main": {},
  "managed-media-source": {},
  "manifest": {
    "percentageOfPageLoad": 0.21489186,
    "chromeStatusUrl": "https://chromestatus.com/metrics/webfeature/timeline/popularity/302"
  },
  "map": {},
  "margin": {},
  "margin-trim": {},
  "mark": {},
  "marker": {
    "percentageOfPageLoad": 0.11534939,
    "chromeStatusUrl": "https://chromestatus.com/metrics/webfeature/timeline/popularity/197"
  },
  "mask-border": {},
  "mask-type": {},
  "masks": {
    "percentageOfPageLoad": 0.35091104,
    "chromeStatusUrl": "https://chromestatus.com/metrics/webfeature/timeline/popularity/101"
  },
  "masonry": {},
  "matchmedia": {},
  "math-sum-precise": {},
  "mathml": {
    "percentageOfPageLoad": 0.01461033,
    "chromeStatusUrl": "https://chromestatus.com/metrics/webfeature/timeline/popularity/90"
  },
  "measure-memory": {
    "percentageOfPageLoad": 0.00005429,
    "chromeStatusUrl": "https://chromestatus.com/metrics/webfeature/timeline/popularity/288"
  },
  "media-capabilities": {},
  "media-capture": {},
  "media-playback-quality": {
    "percentageOfPageLoad": 0.06216298,
    "chromeStatusUrl": "https://chromestatus.com/metrics/webfeature/timeline/popularity/289"
  },
  "media-pseudos": {},
  "media-queries": {},
  "media-query-range-syntax": {
    "percentageOfPageLoad": 0.11514811,
    "chromeStatusUrl": "https://chromestatus.com/metrics/webfeature/timeline/popularity/145"
  },
  "media-session": {
    "percentageOfPageLoad": 0.02627181,
    "chromeStatusUrl": "https://chromestatus.com/metrics/webfeature/timeline/popularity/48"
  },
  "media-source": {},
  "mediacontroller": {},
  "mediastream-recording": {},
  "menu": {},
  "messageerror": {},
  "meta": {},
  "meta-application-title": {
    "percentageOfPageLoad": 0.00000202,
    "chromeStatusUrl": "https://chromestatus.com/metrics/webfeature/timeline/popularity/349"
  },
  "meta-text-scale": {
    "percentageOfPageLoad": 0.00000243,
    "chromeStatusUrl": "https://chromestatus.com/metrics/webfeature/timeline/popularity/417"
  },
  "meta-theme-color": {},
  "meter": {},
  "min-max-clamp": {},
  "min-max-content": {},
  "min-max-width-height": {},
  "mix-blend-mode": {},
  "mixed-content": {},
  "modal": {
    "percentageOfPageLoad": 0.02679084,
    "chromeStatusUrl": "https://chromestatus.com/metrics/webfeature/timeline/popularity/187"
  },
  "modulepreload": {},
  "motion-path": {
    "percentageOfPageLoad": 0.0039766,
    "chromeStatusUrl": "https://chromestatus.com/metrics/webfeature/timeline/popularity/188"
  },
  "mouse-events": {},
  "move-before": {
    "percentageOfPageLoad": 0.00000802,
    "chromeStatusUrl": "https://chromestatus.com/metrics/webfeature/timeline/popularity/229"
  },
  "multi-column": {},
  "mutation-events": {},
  "mutationobserver": {},
  "named-color": {},
  "namespace": {},
  "nav": {},
  "navigation": {
    "percentageOfPageLoad": 0.00189908,
    "chromeStatusUrl": "https://chromestatus.com/metrics/webfeature/timeline/popularity/89"
  },
  "navigation-timing": {},
  "navigator": {},
  "nesting": {
    "percentageOfPageLoad": 0.09737095,
    "chromeStatusUrl": "https://chromestatus.com/metrics/webfeature/timeline/popularity/163"
  },
  "network-information": {},
  "non-cookie-storage-access": {
    "percentageOfPageLoad": 0.0005628,
    "chromeStatusUrl": "https://chromestatus.com/metrics/webfeature/timeline/popularity/265"
  },
  "not": {
    "percentageOfPageLoad": 0.83092879,
    "chromeStatusUrl": "https://chromestatus.com/metrics/webfeature/timeline/popularity/343"
  },
  "notifications": {},
  "notifications-apps": {},
  "nth-child": {},
  "nth-child-of": {
    "percentageOfPageLoad": 0.03572908,
    "chromeStatusUrl": "https://chromestatus.com/metrics/webfeature/timeline/popularity/164"
  },
  "nth-of-type": {},
  "nullish-coalescing": {
    "percentageOfPageLoad": 0.41126451,
    "chromeStatusUrl": "https://chromestatus.com/metrics/webfeature/timeline/popularity/379"
  },
  "number": {},
  "numeric-factory-functions": {},
  "numeric-seperators": {},
  "object": {},
  "object-fit": {},
  "object-hasown": {},
  "object-object": {},
  "object-position": {},
  "object-view-box": {
    "percentageOfPageLoad": 0.00041775,
    "chromeStatusUrl": "https://chromestatus.com/metrics/webfeature/timeline/popularity/156"
  },
  "observable": {
    "percentageOfPageLoad": 0.00000181,
    "chromeStatusUrl": "https://chromestatus.com/metrics/webfeature/timeline/popularity/348"
  },
  "oes-element-index-uint": {},
  "oes-fbo-render-mipmap": {
    "percentageOfPageLoad": 0.01314506,
    "chromeStatusUrl": "https://chromestatus.com/metrics/webfeature/timeline/popularity/384"
  },
  "oes-standard-derivatives": {},
  "oes-texture-float": {},
  "oes-texture-float-linear": {},
  "oes-texture-half-float": {},
  "oes-texture-half-float-linear": {},
  "oes-vertex-array-object": {},
  "offline-audio-context": {
    "percentageOfPageLoad": 0.06022189,
    "chromeStatusUrl": "https://chromestatus.com/metrics/webfeature/timeline/popularity/151"
  },
  "offscreen-canvas": {
    "percentageOfPageLoad": 0.07980316,
    "chromeStatusUrl": "https://chromestatus.com/metrics/webfeature/timeline/popularity/49"
  },
  "oklab": {
    "percentageOfPageLoad": 0.02471038,
    "chromeStatusUrl": "https://chromestatus.com/metrics/webfeature/timeline/popularity/170"
  },
  "online": {},
  "opacity": {},
  "opacity-svg": {},
  "open-closed": {},
  "optional-catch-binding": {},
  "orientation-sensor": {},
  "origin-private-file-system": {
    "percentageOfPageLoad": 0.00287214,
    "chromeStatusUrl": "https://chromestatus.com/metrics/webfeature/timeline/popularity/50"
  },
  "outline": {
    "percentageOfPageLoad": 0.77035973,
    "chromeStatusUrl": "https://chromestatus.com/metrics/webfeature/timeline/popularity/189"
  },
  "outlines": {},
  "output": {},
  "overflow": {
    "percentageOfPageLoad": 0.00323731,
    "chromeStatusUrl": "https://chromestatus.com/metrics/webfeature/timeline/popularity/190"
  },
  "overflow-anchor": {},
  "overflow-clip": {
    "percentageOfPageLoad": 0.18530143,
    "chromeStatusUrl": "https://chromestatus.com/metrics/webfeature/timeline/popularity/336"
  },
  "overflow-clip-margin": {},
  "overflow-overlay": {},
  "overflow-shorthand": {
    "percentageOfPageLoad": 0.14703188,
    "chromeStatusUrl": "https://chromestatus.com/metrics/webfeature/timeline/popularity/112"
  },
  "overflow-wrap": {},
  "overlay": {
    "percentageOfPageLoad": 0.00043737,
    "chromeStatusUrl": "https://chromestatus.com/metrics/webfeature/timeline/popularity/134"
  },
  "overscroll-behavior": {},
  "ovr-multiview2": {},
  "p": {},
  "padding": {},
  "page-break-aliases": {},
  "page-breaks": {},
  "page-lifecycle": {},
  "page-orientation": {
    "percentageOfPageLoad": 0.01591607,
    "chromeStatusUrl": "https://chromestatus.com/metrics/webfeature/timeline/popularity/219"
  },
  "page-selectors": {},
  "page-setup": {},
  "page-transition-events": {},
  "page-visibility": {},
  "page-visibility-state": {
    "percentageOfPageLoad": 0.0057636,
    "chromeStatusUrl": "https://chromestatus.com/metrics/webfeature/timeline/popularity/237"
  },
  "paint": {},
  "paint-order": {
    "percentageOfPageLoad": 0.01519364,
    "chromeStatusUrl": "https://chromestatus.com/metrics/webfeature/timeline/popularity/126"
  },
  "paint-timing": {},
  "parse-html-unsafe": {
    "percentageOfPageLoad": 0.000358,
    "chromeStatusUrl": "https://chromestatus.com/metrics/webfeature/timeline/popularity/122"
  },
  "partitioned-cookies": {
    "percentageOfPageLoad": 0.238886,
    "chromeStatusUrl": "https://chromestatus.com/metrics/webfeature/timeline/popularity/419"
  },
  "password-credentials": {},
  "path-shape": {},
  "payment-handler": {},
  "payment-request": {},
  "pdf-viewer": {
    "percentageOfPageLoad": 0.06188353,
    "chromeStatusUrl": "https://chromestatus.com/metrics/webfeature/timeline/popularity/257"
  },
  "performance": {},
  "performancetiming": {},
  "periodic-background-sync": {},
  "permissions": {},
  "physical-properties": {},
  "picture": {},
  "picture-in-picture": {
    "percentageOfPageLoad": 0.00014085,
    "chromeStatusUrl": "https://chromestatus.com/metrics/webfeature/timeline/popularity/51"
  },
  "ping": {},
  "placeholder": {},
  "placeholder-shown": {},
  "pointer-events": {},
  "pointer-events-api": {},
  "pointer-lock": {
    "percentageOfPageLoad": 0.0007121,
    "chromeStatusUrl": "https://chromestatus.com/metrics/webfeature/timeline/popularity/52"
  },
  "popover": {
    "percentageOfPageLoad": 0.0216215,
    "chromeStatusUrl": "https://chromestatus.com/metrics/webfeature/timeline/popularity/374"
  },
  "popover-hint": {
    "percentageOfPageLoad": 0.00027088,
    "chromeStatusUrl": "https://chromestatus.com/metrics/webfeature/timeline/popularity/296"
  },
  "portal": {},
  "position": {},
  "postmessage": {},
  "pre": {},
  "prefers-color-scheme": {},
  "prefers-contrast": {
    "percentageOfPageLoad": 0.23503687,
    "chromeStatusUrl": "https://chromestatus.com/metrics/webfeature/timeline/popularity/174"
  },
  "prefers-reduced-data": {},
  "prefers-reduced-motion": {},
  "prefers-reduced-transparency": {
    "percentageOfPageLoad": 0.03948478,
    "chromeStatusUrl": "https://chromestatus.com/metrics/webfeature/timeline/popularity/175"
  },
  "preloading-responsive-images": {},
  "presentation-api": {},
  "preserves-pitch": {
    "percentageOfPageLoad": 0.00011461,
    "chromeStatusUrl": "https://chromestatus.com/metrics/webfeature/timeline/popularity/249"
  },
  "print": {},
  "print-color-adjust": {
    "percentageOfPageLoad": 0.02927348,
    "chromeStatusUrl": "https://chromestatus.com/metrics/webfeature/timeline/popularity/330"
  },
  "print-events": {},
  "private-click-measurement": {},
  "private-network-access": {},
  "profiler": {
    "percentageOfPageLoad": 0.00087208,
    "chromeStatusUrl": "https://chromestatus.com/metrics/webfeature/timeline/popularity/278"
  },
  "progress": {},
  "promise": {},
  "promise-allsettled": {},
  "promise-any": {
    "percentageOfPageLoad": 0.0242473,
    "chromeStatusUrl": "https://chromestatus.com/metrics/webfeature/timeline/popularity/226"
  },
  "promise-finally": {},
  "promise-try": {
    "percentageOfPageLoad": 0.04365666,
    "chromeStatusUrl": "https://chromestatus.com/metrics/webfeature/timeline/popularity/251"
  },
  "promise-withresolvers": {
    "percentageOfPageLoad": 0.02867403,
    "chromeStatusUrl": "https://chromestatus.com/metrics/webfeature/timeline/popularity/240"
  },
  "proto": {},
  "proxy-reflect": {},
  "push": {},
  "q": {},
  "q-unit": {},
  "quotes": {
    "percentageOfPageLoad": 0.08524032,
    "chromeStatusUrl": "https://chromestatus.com/metrics/webfeature/timeline/popularity/213"
  },
  "rcap": {
    "percentageOfPageLoad": 0.00002665,
    "chromeStatusUrl": "https://chromestatus.com/metrics/webfeature/timeline/popularity/158"
  },
  "rch": {
    "percentageOfPageLoad": 9.2e-7,
    "chromeStatusUrl": "https://chromestatus.com/metrics/webfeature/timeline/popularity/207"
  },
  "read-write-pseudos": {},
  "readable-byte-streams": {
    "percentageOfPageLoad": 0.00026884,
    "chromeStatusUrl": "https://chromestatus.com/metrics/webfeature/timeline/popularity/400"
  },
  "readablestream-from": {},
  "reading-flow": {
    "percentageOfPageLoad": 0.0003815,
    "chromeStatusUrl": "https://chromestatus.com/metrics/webfeature/timeline/popularity/313"
  },
  "referencetarget": {
    "percentageOfPageLoad": 0.00010148,
    "chromeStatusUrl": "https://chromestatus.com/metrics/webfeature/timeline/popularity/246"
  },
  "referrer-policy": {
    "percentageOfPageLoad": 0.33867342,
    "chromeStatusUrl": "https://chromestatus.com/metrics/webfeature/timeline/popularity/260"
  },
  "regexp": {},
  "regexp-compile": {
    "percentageOfPageLoad": 0.00385048,
    "chromeStatusUrl": "https://chromestatus.com/metrics/webfeature/timeline/popularity/392"
  },
  "regexp-escape": {
    "percentageOfPageLoad": 0.02078077,
    "chromeStatusUrl": "https://chromestatus.com/metrics/webfeature/timeline/popularity/297"
  },
  "regexp-static-properties": {
    "percentageOfPageLoad": 0.06295758,
    "chromeStatusUrl": "https://chromestatus.com/metrics/webfeature/timeline/popularity/395"
  },
  "region-capture": {
    "percentageOfPageLoad": 0.0008435,
    "chromeStatusUrl": "https://chromestatus.com/metrics/webfeature/timeline/popularity/322"
  },
  "registered-custom-properties": {
    "percentageOfPageLoad": 0.08000628,
    "chromeStatusUrl": "https://chromestatus.com/metrics/webfeature/timeline/popularity/146"
  },
  "registerprotocolhandler": {},
  "relative-color": {
    "percentageOfPageLoad": 0.04562818,
    "chromeStatusUrl": "https://chromestatus.com/metrics/webfeature/timeline/popularity/53"
  },
  "relative-positioning": {},
  "rem": {},
  "remote-playback": {
    "percentageOfPageLoad": 0.00315395,
    "chromeStatusUrl": "https://chromestatus.com/metrics/webfeature/timeline/popularity/255"
  },
  "reporting": {
    "percentageOfPageLoad": 0.30644074,
    "chromeStatusUrl": "https://chromestatus.com/metrics/webfeature/timeline/popularity/410"
  },
  "request-animation-frame": {
    "percentageOfPageLoad": 0.61405281,
    "chromeStatusUrl": "https://chromestatus.com/metrics/webfeature/timeline/popularity/323"
  },
  "request-animation-frame-workers": {
    "percentageOfPageLoad": 0.00155615,
    "chromeStatusUrl": "https://chromestatus.com/metrics/webfeature/timeline/popularity/324"
  },
  "request-video-frame-callback": {
    "percentageOfPageLoad": 0.0069332,
    "chromeStatusUrl": "https://chromestatus.com/metrics/webfeature/timeline/popularity/154"
  },
  "requestclose": {
    "percentageOfPageLoad": 9.5e-7,
    "chromeStatusUrl": "https://chromestatus.com/metrics/webfeature/timeline/popularity/333"
  },
  "requestidlecallback": {
    "percentageOfPageLoad": 0.45189575,
    "chromeStatusUrl": "https://chromestatus.com/metrics/webfeature/timeline/popularity/338"
  },
  "resizable-buffers": {
    "percentageOfPageLoad": 0.00433181,
    "chromeStatusUrl": "https://chromestatus.com/metrics/webfeature/timeline/popularity/221"
  },
  "resize": {},
  "resize-observer": {},
  "resolution": {},
  "resolution-compat": {},
  "resource-size": {},
  "resource-timing": {},
  "revert-value": {
    "percentageOfPageLoad": 0.03127642,
    "chromeStatusUrl": "https://chromestatus.com/metrics/webfeature/timeline/popularity/173"
  },
  "rex": {},
  "rgb": {},
  "rhythmic-sizing": {},
  "ric": {
    "percentageOfPageLoad": 1e-8,
    "chromeStatusUrl": "https://chromestatus.com/metrics/webfeature/timeline/popularity/160"
  },
  "rlh": {
    "percentageOfPageLoad": 0.00002291,
    "chromeStatusUrl": "https://chromestatus.com/metrics/webfeature/timeline/popularity/162"
  },
  "root": {},
  "round-mod-rem": {
    "percentageOfPageLoad": 0.01094408,
    "chromeStatusUrl": "https://chromestatus.com/metrics/webfeature/timeline/popularity/176"
  },
  "ruby": {},
  "ruby-align": {
    "percentageOfPageLoad": 0.00191118,
    "chromeStatusUrl": "https://chromestatus.com/metrics/webfeature/timeline/popularity/208"
  },
  "ruby-overhang": {},
  "ruby-position": {
    "percentageOfPageLoad": 0.00203675,
    "chromeStatusUrl": "https://chromestatus.com/metrics/webfeature/timeline/popularity/209"
  },
  "s": {},
  "safe-area-inset": {},
  "samp": {},
  "sanitizer": {},
  "savedata": {},
  "scheduler": {
    "percentageOfPageLoad": 0.09960392,
    "chromeStatusUrl": "https://chromestatus.com/metrics/webfeature/timeline/popularity/118"
  },
  "scope": {
    "percentageOfPageLoad": 0.00133254,
    "chromeStatusUrl": "https://chromestatus.com/metrics/webfeature/timeline/popularity/54"
  },
  "scope-pseudo": {},
  "scoped-custom-element-registries": {},
  "screen": {},
  "screen-capture": {},
  "screen-orientation": {},
  "screen-orientation-lock": {},
  "screen-wake-lock": {
    "percentageOfPageLoad": 0.01334497,
    "chromeStatusUrl": "https://chromestatus.com/metrics/webfeature/timeline/popularity/104"
  },
  "script": {},
  "scripting": {
    "percentageOfPageLoad": 0.00744223,
    "chromeStatusUrl": "https://chromestatus.com/metrics/webfeature/timeline/popularity/344"
  },
  "scroll-behavior": {},
  "scroll-buttons": {
    "percentageOfPageLoad": 0.00006711,
    "chromeStatusUrl": "https://chromestatus.com/metrics/webfeature/timeline/popularity/294"
  },
  "scroll-driven-animations": {
    "percentageOfPageLoad": 0.03450443,
    "chromeStatusUrl": "https://chromestatus.com/metrics/webfeature/timeline/popularity/230"
  },
  "scroll-elements": {},
  "scroll-initial-target": {
    "percentageOfPageLoad": 0.0002032,
    "chromeStatusUrl": "https://chromestatus.com/metrics/webfeature/timeline/popularity/319"
  },
  "scroll-into-view": {},
  "scroll-markers": {
    "percentageOfPageLoad": 0.00047962,
    "chromeStatusUrl": "https://chromestatus.com/metrics/webfeature/timeline/popularity/295"
  },
  "scroll-snap": {
    "percentageOfPageLoad": 0.15916146,
    "chromeStatusUrl": "https://chromestatus.com/metrics/webfeature/timeline/popularity/59"
  },
  "scroll-snap-events": {
    "percentageOfPageLoad": 0.00072772,
    "chromeStatusUrl": "https://chromestatus.com/metrics/webfeature/timeline/popularity/228"
  },
  "scroll-to-text-fragment": {
    "percentageOfPageLoad": 0.00105397,
    "chromeStatusUrl": "https://chromestatus.com/metrics/webfeature/timeline/popularity/60"
  },
  "scrollbar-color": {
    "percentageOfPageLoad": 0.15817903,
    "chromeStatusUrl": "https://chromestatus.com/metrics/webfeature/timeline/popularity/55"
  },
  "scrollbar-gutter": {
    "percentageOfPageLoad": 0.12909721,
    "chromeStatusUrl": "https://chromestatus.com/metrics/webfeature/timeline/popularity/56"
  },
  "scrollbar-width": {
    "percentageOfPageLoad": 0.38436778,
    "chromeStatusUrl": "https://chromestatus.com/metrics/webfeature/timeline/popularity/57"
  },
  "scrollend": {
    "percentageOfPageLoad": 0.25521921,
    "chromeStatusUrl": "https://chromestatus.com/metrics/webfeature/timeline/popularity/58"
  },
  "search": {
    "percentageOfPageLoad": 0.00235429,
    "chromeStatusUrl": "https://chromestatus.com/metrics/webfeature/timeline/popularity/120"
  },
  "search-input-type": {},
  "section": {},
  "secure-payment-confirmation": {},
  "select": {},
  "selection": {},
  "selection-api": {},
  "selectors": {},
  "serial": {
    "percentageOfPageLoad": 0.00001807,
    "chromeStatusUrl": "https://chromestatus.com/metrics/webfeature/timeline/popularity/107"
  },
  "serializable-errors": {},
  "server-sent-events": {},
  "server-timing": {},
  "service-workers": {},
  "set": {},
  "set-methods": {
    "percentageOfPageLoad": 0.05556651,
    "chromeStatusUrl": "https://chromestatus.com/metrics/webfeature/timeline/popularity/227"
  },
  "setinterval": {},
  "settimeout": {},
  "shadow-dom": {},
  "shadow-parts": {},
  "shape-outside": {},
  "shapes": {},
  "share": {},
  "shared-memory": {},
  "shared-storage": {},
  "shared-storage-locks": {},
  "shared-workers": {},
  "show-picker-input": {
    "percentageOfPageLoad": 0.00002234,
    "chromeStatusUrl": "https://chromestatus.com/metrics/webfeature/timeline/popularity/61"
  },
  "show-picker-select": {
    "percentageOfPageLoad": 0.00000197,
    "chromeStatusUrl": "https://chromestatus.com/metrics/webfeature/timeline/popularity/127"
  },
  "sibling-count": {},
  "single-color-gradients": {},
  "sizes-auto": {
    "percentageOfPageLoad": 0.00825516,
    "chromeStatusUrl": "https://chromestatus.com/metrics/webfeature/timeline/popularity/346"
  },
  "slot": {
    "percentageOfPageLoad": 0.5976086,
    "chromeStatusUrl": "https://chromestatus.com/metrics/webfeature/timeline/popularity/62"
  },
  "slot-assign": {
    "percentageOfPageLoad": 0.00026628,
    "chromeStatusUrl": "https://chromestatus.com/metrics/webfeature/timeline/popularity/100"
  },
  "small": {},
  "smil-svg-animations": {},
  "smooth": {},
  "source": {},
  "sourcemap-header": {},
  "span": {},
  "speak": {},
  "speak-as": {},
  "speculation-rules": {
    "percentageOfPageLoad": 0.11711904,
    "chromeStatusUrl": "https://chromestatus.com/metrics/webfeature/timeline/popularity/317"
  },
  "speech-recognition": {
    "percentageOfPageLoad": 0.0009062,
    "chromeStatusUrl": "https://chromestatus.com/metrics/webfeature/timeline/popularity/63"
  },
  "speech-recognition-grammar": {},
  "speech-synthesis": {
    "percentageOfPageLoad": 0.00093932,
    "chromeStatusUrl": "https://chromestatus.com/metrics/webfeature/timeline/popularity/64"
  },
  "spellcheck": {},
  "spelling-grammar-error": {
    "percentageOfPageLoad": 0.004849,
    "chromeStatusUrl": "https://chromestatus.com/metrics/webfeature/timeline/popularity/192"
  },
  "spread": {},
  "srcset": {},
  "stable-array-sort": {},
  "starting-style": {
    "percentageOfPageLoad": 0.02263077,
    "chromeStatusUrl": "https://chromestatus.com/metrics/webfeature/timeline/popularity/143"
  },
  "state": {
    "percentageOfPageLoad": 0.00147835,
    "chromeStatusUrl": "https://chromestatus.com/metrics/webfeature/timeline/popularity/329"
  },
  "static-positioning": {},
  "steps-easing": {},
  "sticky-positioning": {},
  "storage-access": {
    "percentageOfPageLoad": 0.03167012,
    "chromeStatusUrl": "https://chromestatus.com/metrics/webfeature/timeline/popularity/65"
  },
  "storage-buckets": {
    "percentageOfPageLoad": 0.00128776,
    "chromeStatusUrl": "https://chromestatus.com/metrics/webfeature/timeline/popularity/66"
  },
  "storage-manager": {},
  "streams": {},
  "stretch": {},
  "string-at": {},
  "string-codepoint": {},
  "string-includes": {},
  "string-matchall": {},
  "string-normalize": {},
  "string-pad": {},
  "string-raw": {},
  "string-repeat": {},
  "string-replaceall": {
    "percentageOfPageLoad": 0.3169157,
    "chromeStatusUrl": "https://chromestatus.com/metrics/webfeature/timeline/popularity/252"
  },
  "string-startsends-with": {},
  "string-trim-startend": {},
  "string-wellformed": {
    "percentageOfPageLoad": 0.06751621,
    "chromeStatusUrl": "https://chromestatus.com/metrics/webfeature/timeline/popularity/253"
  },
  "strings": {},
  "strong": {},
  "structured-clone": {
    "percentageOfPageLoad": 0.22071503,
    "chromeStatusUrl": "https://chromestatus.com/metrics/webfeature/timeline/popularity/99"
  },
  "style": {},
  "style-attr": {},
  "sub-sup": {},
  "subgrid": {
    "percentageOfPageLoad": 0.00403515,
    "chromeStatusUrl": "https://chromestatus.com/metrics/webfeature/timeline/popularity/4"
  },
  "summarizer": {
    "percentageOfPageLoad": 1e-8,
    "chromeStatusUrl": "https://chromestatus.com/metrics/webfeature/timeline/popularity/415"
  },
  "supports": {},
  "supports-compat": {},
  "svg": {},
  "svg-discouraged": {},
  "svg-filters": {},
  "symbol": {},
  "system-color": {},
  "tab-size": {},
  "tabindex": {},
  "table": {},
  "table-discouraged": {},
  "target": {},
  "target-text": {
    "percentageOfPageLoad": 0.00056957,
    "chromeStatusUrl": "https://chromestatus.com/metrics/webfeature/timeline/popularity/67"
  },
  "target-within": {},
  "template": {
    "percentageOfPageLoad": 0.31793735,
    "chromeStatusUrl": "https://chromestatus.com/metrics/webfeature/timeline/popularity/68"
  },
  "template-literals": {},
  "temporal": {},
  "text-align": {},
  "text-align-last": {},
  "text-autospace": {},
  "text-box": {
    "percentageOfPageLoad": 0.00815152,
    "chromeStatusUrl": "https://chromestatus.com/metrics/webfeature/timeline/popularity/318"
  },
  "text-combine-upright": {},
  "text-decoration": {},
  "text-decoration-line-blink": {},
  "text-decoration-selection": {},
  "text-detect": {
    "percentageOfPageLoad": 1e-8,
    "chromeStatusUrl": "https://chromestatus.com/metrics/webfeature/timeline/popularity/413"
  },
  "text-emphasis": {
    "percentageOfPageLoad": 0.00253345,
    "chromeStatusUrl": "https://chromestatus.com/metrics/webfeature/timeline/popularity/180"
  },
  "text-encoding": {},
  "text-indent": {
    "percentageOfPageLoad": 0.36335629,
    "chromeStatusUrl": "https://chromestatus.com/metrics/webfeature/timeline/popularity/69"
  },
  "text-indent-each-line": {},
  "text-indent-hanging": {},
  "text-justify": {
    "percentageOfPageLoad": 0.00533901,
    "chromeStatusUrl": "https://chromestatus.com/metrics/webfeature/timeline/popularity/414"
  },
  "text-orientation": {},
  "text-overflow": {},
  "text-shadow": {},
  "text-size-adjust": {},
  "text-spacing-trim": {
    "percentageOfPageLoad": 0.00605208,
    "chromeStatusUrl": "https://chromestatus.com/metrics/webfeature/timeline/popularity/70"
  },
  "text-stroke-fill": {},
  "text-tracks": {},
  "text-transform": {},
  "text-underline-offset": {
    "percentageOfPageLoad": 0.15730307,
    "chromeStatusUrl": "https://chromestatus.com/metrics/webfeature/timeline/popularity/331"
  },
  "text-underline-position": {},
  "text-wrap": {
    "percentageOfPageLoad": 0.21444445,
    "chromeStatusUrl": "https://chromestatus.com/metrics/webfeature/timeline/popularity/181"
  },
  "text-wrap-balance": {
    "percentageOfPageLoad": 0.01875389,
    "chromeStatusUrl": "https://chromestatus.com/metrics/webfeature/timeline/popularity/71"
  },
  "text-wrap-mode": {},
  "text-wrap-nowrap": {},
  "text-wrap-pretty": {
    "percentageOfPageLoad": 0.0161963,
    "chromeStatusUrl": "https://chromestatus.com/metrics/webfeature/timeline/popularity/72"
  },
  "text-wrap-stable": {},
  "text-wrap-style": {
    "percentageOfPageLoad": 0.00103394,
    "chromeStatusUrl": "https://chromestatus.com/metrics/webfeature/timeline/popularity/182"
  },
  "textarea": {},
  "time": {},
  "time-relative-selectors": {
    "percentageOfPageLoad": 0.00191392,
    "chromeStatusUrl": "https://chromestatus.com/metrics/webfeature/timeline/popularity/355"
  },
  "title": {},
  "title-attr": {},
  "top-level-await": {
    "percentageOfPageLoad": 0.00950313,
    "chromeStatusUrl": "https://chromestatus.com/metrics/webfeature/timeline/popularity/376"
  },
  "touch-action": {},
  "touch-events": {},
  "transferable-arraybuffer": {
    "percentageOfPageLoad": 0.00112255,
    "chromeStatusUrl": "https://chromestatus.com/metrics/webfeature/timeline/popularity/241"
  },
  "transferable-streams": {
    "percentageOfPageLoad": 0.00174898,
    "chromeStatusUrl": "https://chromestatus.com/metrics/webfeature/timeline/popularity/399"
  },
  "transform-box": {
    "percentageOfPageLoad": 0.04042056,
    "chromeStatusUrl": "https://chromestatus.com/metrics/webfeature/timeline/popularity/194"
  },
  "transforms2d": {},
  "transforms3d": {},
  "transformstream-transformer-cancel": {},
  "transition-behavior": {
    "percentageOfPageLoad": 0.0071405,
    "chromeStatusUrl": "https://chromestatus.com/metrics/webfeature/timeline/popularity/73"
  },
  "transitions": {},
  "translate": {},
  "translation-api": {
    "percentageOfPageLoad": 0.00119951,
    "chromeStatusUrl": "https://chromestatus.com/metrics/webfeature/timeline/popularity/416"
  },
  "trig-functions": {
    "percentageOfPageLoad": 0.00459211,
    "chromeStatusUrl": "https://chromestatus.com/metrics/webfeature/timeline/popularity/177"
  },
  "trusted-types": {},
  "two-value-display": {
    "percentageOfPageLoad": 0.00366164,
    "chromeStatusUrl": "https://chromestatus.com/metrics/webfeature/timeline/popularity/111"
  },
  "typed-array-iteration-methods": {},
  "typed-array-iterators": {},
  "typed-arrays": {},
  "u": {},
  "ua-client-hints": {
    "percentageOfPageLoad": 0.74136697,
    "chromeStatusUrl": "https://chromestatus.com/metrics/webfeature/timeline/popularity/341"
  },
  "uint-8array-base-64hex": {
    "percentageOfPageLoad": 0.01784741,
    "chromeStatusUrl": "https://chromestatus.com/metrics/webfeature/timeline/popularity/334"
  },
  "uint8array-base64-hex": {},
  "unicode-point-escapes": {},
  "unset-value": {},
  "update": {
    "percentageOfPageLoad": 0.00729316,
    "chromeStatusUrl": "https://chromestatus.com/metrics/webfeature/timeline/popularity/195"
  },
  "upgrade-insecure-requests": {},
  "url": {},
  "url-canparse": {
    "percentageOfPageLoad": 0.05434373,
    "chromeStatusUrl": "https://chromestatus.com/metrics/webfeature/timeline/popularity/261"
  },
  "urlpattern": {
    "percentageOfPageLoad": 0.02011749,
    "chromeStatusUrl": "https://chromestatus.com/metrics/webfeature/timeline/popularity/326"
  },
  "user-action-pseudos": {},
  "user-activation": {},
  "user-agent-sniffing": {},
  "user-pseudos": {
    "percentageOfPageLoad": 0.00322619,
    "chromeStatusUrl": "https://chromestatus.com/metrics/webfeature/timeline/popularity/75"
  },
  "user-select": {},
  "var": {},
  "vertical-align": {},
  "vertical-form-controls": {
    "percentageOfPageLoad": 0.00035162,
    "chromeStatusUrl": "https://chromestatus.com/metrics/webfeature/timeline/popularity/256"
  },
  "vibration": {},
  "video": {},
  "video-dynamic-range": {},
  "view-transition-class": {
    "percentageOfPageLoad": 0.00082238,
    "chromeStatusUrl": "https://chromestatus.com/metrics/webfeature/timeline/popularity/245"
  },
  "view-transitions": {
    "percentageOfPageLoad": 0.00558127,
    "chromeStatusUrl": "https://chromestatus.com/metrics/webfeature/timeline/popularity/2"
  },
  "view-transitions-element-scoped": {
    "percentageOfPageLoad": 0.000412,
    "chromeStatusUrl": "https://chromestatus.com/metrics/webfeature/timeline/popularity/281"
  },
  "viewport-segments": {},
  "viewport-unit-variants": {
    "percentageOfPageLoad": 0.14428195,
    "chromeStatusUrl": "https://chromestatus.com/metrics/webfeature/timeline/popularity/250"
  },
  "viewport-units": {},
  "virtual-keyboard": {
    "percentageOfPageLoad": 0.00375892,
    "chromeStatusUrl": "https://chromestatus.com/metrics/webfeature/timeline/popularity/264"
  },
  "virtual-pressure-sources": {},
  "virtual-sensors": {},
  "visibility": {},
  "visual-viewport": {},
  "wasm": {},
  "wasm-bigint": {},
  "wasm-bulk-memory": {
    "percentageOfPageLoad": 0.01529106,
    "chromeStatusUrl": "https://chromestatus.com/metrics/webfeature/timeline/popularity/369"
  },
  "wasm-exception-handling": {
    "percentageOfPageLoad": 0.0042745,
    "chromeStatusUrl": "https://chromestatus.com/metrics/webfeature/timeline/popularity/356"
  },
  "wasm-exnref-exceptions": {
    "percentageOfPageLoad": 6e-8,
    "chromeStatusUrl": "https://chromestatus.com/metrics/webfeature/timeline/popularity/367"
  },
  "wasm-extended-constant-expressions": {},
  "wasm-garbage-collection": {
    "percentageOfPageLoad": 0.00373853,
    "chromeStatusUrl": "https://chromestatus.com/metrics/webfeature/timeline/popularity/358"
  },
  "wasm-memory-64": {
    "percentageOfPageLoad": 0.00000137,
    "chromeStatusUrl": "https://chromestatus.com/metrics/webfeature/timeline/popularity/366"
  },
  "wasm-memory64": {},
  "wasm-multi-memory": {
    "percentageOfPageLoad": 5.6e-7,
    "chromeStatusUrl": "https://chromestatus.com/metrics/webfeature/timeline/popularity/359"
  },
  "wasm-multi-value": {
    "percentageOfPageLoad": 0.00358966,
    "chromeStatusUrl": "https://chromestatus.com/metrics/webfeature/timeline/popularity/368"
  },
  "wasm-mutable-globals": {
    "percentageOfPageLoad": 0.00024213,
    "chromeStatusUrl": "https://chromestatus.com/metrics/webfeature/timeline/popularity/370"
  },
  "wasm-non-trapping-float-to-int": {
    "percentageOfPageLoad": 0.00936372,
    "chromeStatusUrl": "https://chromestatus.com/metrics/webfeature/timeline/popularity/371"
  },
  "wasm-reference-types": {
    "percentageOfPageLoad": 0.00654822,
    "chromeStatusUrl": "https://chromestatus.com/metrics/webfeature/timeline/popularity/360"
  },
  "wasm-sign-extension-operators": {
    "percentageOfPageLoad": 0.02881134,
    "chromeStatusUrl": "https://chromestatus.com/metrics/webfeature/timeline/popularity/372"
  },
  "wasm-simd": {
    "percentageOfPageLoad": 0.00308197,
    "chromeStatusUrl": "https://chromestatus.com/metrics/webfeature/timeline/popularity/347"
  },
  "wasm-simd-relaxed": {
    "percentageOfPageLoad": 0.00008307,
    "chromeStatusUrl": "https://chromestatus.com/metrics/webfeature/timeline/popularity/361"
  },
  "wasm-string-builtins": {
    "percentageOfPageLoad": 0.00373245,
    "chromeStatusUrl": "https://chromestatus.com/metrics/webfeature/timeline/popularity/364"
  },
  "wasm-tail-call-optimization": {
    "percentageOfPageLoad": 6.1e-7,
    "chromeStatusUrl": "https://chromestatus.com/metrics/webfeature/timeline/popularity/362"
  },
  "wasm-threads": {
    "percentageOfPageLoad": 0.00071838,
    "chromeStatusUrl": "https://chromestatus.com/metrics/webfeature/timeline/popularity/363"
  },
  "wasm-typed-fun-refs": {
    "percentageOfPageLoad": 0.00373426,
    "chromeStatusUrl": "https://chromestatus.com/metrics/webfeature/timeline/popularity/365"
  },
  "wbr": {},
  "weak-references": {
    "percentageOfPageLoad": 0.14713778,
    "chromeStatusUrl": "https://chromestatus.com/metrics/webfeature/timeline/popularity/254"
  },
  "weakmap": {},
  "weakset": {},
  "web-animations": {
    "percentageOfPageLoad": 0.15396581,
    "chromeStatusUrl": "https://chromestatus.com/metrics/webfeature/timeline/popularity/231"
  },
  "web-audio": {
    "percentageOfPageLoad": 0.03453771,
    "chromeStatusUrl": "https://chromestatus.com/metrics/webfeature/timeline/popularity/150"
  },
  "web-bluetooth": {
    "percentageOfPageLoad": 0.00001047,
    "chromeStatusUrl": "https://chromestatus.com/metrics/webfeature/timeline/popularity/105"
  },
  "web-cryptography": {},
  "web-locks": {
    "percentageOfPageLoad": 0.04106955,
    "chromeStatusUrl": "https://chromestatus.com/metrics/webfeature/timeline/popularity/78"
  },
  "web-midi": {
    "percentageOfPageLoad": 0.00009658,
    "chromeStatusUrl": "https://chromestatus.com/metrics/webfeature/timeline/popularity/153"
  },
  "web-nfc": {
    "percentageOfPageLoad": 0.00001581,
    "chromeStatusUrl": "https://chromestatus.com/metrics/webfeature/timeline/popularity/106"
  },
  "web-otp": {
    "percentageOfPageLoad": 0.00025781,
    "chromeStatusUrl": "https://chromestatus.com/metrics/webfeature/timeline/popularity/248"
  },
  "webauthn": {},
  "webauthn-public-key-easy": {
    "percentageOfPageLoad": 0.00000404,
    "chromeStatusUrl": "https://chromestatus.com/metrics/webfeature/timeline/popularity/327"
  },
  "webauthn-signals": {},
  "webcodecs": {
    "percentageOfPageLoad": 0.00084947,
    "chromeStatusUrl": "https://chromestatus.com/metrics/webfeature/timeline/popularity/76"
  },
  "webdriver": {},
  "webdriver-bidi": {},
  "webgl": {},
  "webgl-2color-management": {
    "percentageOfPageLoad": 0.00063348,
    "chromeStatusUrl": "https://chromestatus.com/metrics/webfeature/timeline/popularity/390"
  },
  "webgl-2desynchronized": {
    "percentageOfPageLoad": 0.00059162,
    "chromeStatusUrl": "https://chromestatus.com/metrics/webfeature/timeline/popularity/391"
  },
  "webgl-color-buffer-float": {},
  "webgl-color-management": {
    "percentageOfPageLoad": 0.00085045,
    "chromeStatusUrl": "https://chromestatus.com/metrics/webfeature/timeline/popularity/385"
  },
  "webgl-compressed-texture-astc": {},
  "webgl-compressed-texture-etc": {},
  "webgl-compressed-texture-etc1": {},
  "webgl-compressed-texture-pvrtc": {
    "percentageOfPageLoad": 0.00413775,
    "chromeStatusUrl": "https://chromestatus.com/metrics/webfeature/timeline/popularity/386"
  },
  "webgl-compressed-texture-s3tc": {},
  "webgl-compressed-texture-s3tc-srgb": {},
  "webgl-debug-renderer-info": {},
  "webgl-debug-shaders": {},
  "webgl-depth-texture": {},
  "webgl-desynchronized": {
    "percentageOfPageLoad": 0.00095445,
    "chromeStatusUrl": "https://chromestatus.com/metrics/webfeature/timeline/popularity/387"
  },
  "webgl-draw-buffers": {},
  "webgl-lose-context": {},
  "webgl-multi-draw": {
    "percentageOfPageLoad": 0.0153924,
    "chromeStatusUrl": "https://chromestatus.com/metrics/webfeature/timeline/popularity/388"
  },
  "webgl-oes-draw-buffers-indexed": {
    "percentageOfPageLoad": 0.00452845,
    "chromeStatusUrl": "https://chromestatus.com/metrics/webfeature/timeline/popularity/389"
  },
  "webgl-sab": {},
  "webgl2": {},
  "webgl2-color-management": {},
  "webgl2-desynchronized": {},
  "webgpu": {
    "percentageOfPageLoad": 0.0138975,
    "chromeStatusUrl": "https://chromestatus.com/metrics/webfeature/timeline/popularity/290"
  },
  "webhid": {
    "percentageOfPageLoad": 0.0000112,
    "chromeStatusUrl": "https://chromestatus.com/metrics/webfeature/timeline/popularity/77"
  },
  "webnn": {
    "percentageOfPageLoad": 1e-8,
    "chromeStatusUrl": "https://chromestatus.com/metrics/webfeature/timeline/popularity/412"
  },
  "webp": {
    "percentageOfPageLoad": 0.41924521,
    "chromeStatusUrl": "https://chromestatus.com/metrics/webfeature/timeline/popularity/79"
  },
  "webrtc": {},
  "webrtc-encoded-transform": {},
  "webrtc-sctp": {},
  "webrtc-stats": {},
  "websockets": {},
  "webtransport": {
    "percentageOfPageLoad": 0.00002277,
    "chromeStatusUrl": "https://chromestatus.com/metrics/webfeature/timeline/popularity/80"
  },
  "webusb": {
    "percentageOfPageLoad": 0.0000174,
    "chromeStatusUrl": "https://chromestatus.com/metrics/webfeature/timeline/popularity/81"
  },
  "webvr": {},
  "webvtt": {
    "percentageOfPageLoad": 0.054152,
    "chromeStatusUrl": "https://chromestatus.com/metrics/webfeature/timeline/popularity/82"
  },
  "webvtt-cue-alignment": {},
  "webvtt-cue-settings": {},
  "webvtt-regions": {},
  "webxr-anchors": {
    "percentageOfPageLoad": 1e-8,
    "chromeStatusUrl": "https://chromestatus.com/metrics/webfeature/timeline/popularity/402"
  },
  "webxr-ar": {
    "percentageOfPageLoad": 1.5e-7,
    "chromeStatusUrl": "https://chromestatus.com/metrics/webfeature/timeline/popularity/403"
  },
  "webxr-camera": {
    "percentageOfPageLoad": 1e-8,
    "chromeStatusUrl": "https://chromestatus.com/metrics/webfeature/timeline/popularity/404"
  },
  "webxr-depth-sensing": {
    "percentageOfPageLoad": 2e-8,
    "chromeStatusUrl": "https://chromestatus.com/metrics/webfeature/timeline/popularity/405"
  },
  "webxr-device": {},
  "webxr-dom-overlays": {
    "percentageOfPageLoad": 1.5e-7,
    "chromeStatusUrl": "https://chromestatus.com/metrics/webfeature/timeline/popularity/406"
  },
  "webxr-gamepads": {},
  "webxr-hand-input": {
    "percentageOfPageLoad": 1e-7,
    "chromeStatusUrl": "https://chromestatus.com/metrics/webfeature/timeline/popularity/407"
  },
  "webxr-hit-test": {
    "percentageOfPageLoad": 1.2e-7,
    "chromeStatusUrl": "https://chromestatus.com/metrics/webfeature/timeline/popularity/408"
  },
  "webxr-layers": {},
  "webxr-lighting-estimation": {
    "percentageOfPageLoad": 8e-8,
    "chromeStatusUrl": "https://chromestatus.com/metrics/webfeature/timeline/popularity/409"
  },
  "wheel-events": {},
  "where": {
    "percentageOfPageLoad": 0.30143646,
    "chromeStatusUrl": "https://chromestatus.com/metrics/webfeature/timeline/popularity/83"
  },
  "white-space": {},
  "white-space-collapse": {
    "percentageOfPageLoad": 0.00739354,
    "chromeStatusUrl": "https://chromestatus.com/metrics/webfeature/timeline/popularity/166"
  },
  "widows-orphans": {},
  "width-height": {},
  "will-change": {
    "percentageOfPageLoad": 0.37235007,
    "chromeStatusUrl": "https://chromestatus.com/metrics/webfeature/timeline/popularity/87"
  },
  "window": {},
  "window-controls-overlay": {
    "percentageOfPageLoad": 0.00144385,
    "chromeStatusUrl": "https://chromestatus.com/metrics/webfeature/timeline/popularity/267"
  },
  "window-management": {
    "percentageOfPageLoad": 0.00034872,
    "chromeStatusUrl": "https://chromestatus.com/metrics/webfeature/timeline/popularity/332"
  },
  "with": {
    "percentageOfPageLoad": 0.07930055,
    "chromeStatusUrl": "https://chromestatus.com/metrics/webfeature/timeline/popularity/393"
  },
  "word-break": {},
  "word-break-auto-phrase": {
    "percentageOfPageLoad": 0.00048093,
    "chromeStatusUrl": "https://chromestatus.com/metrics/webfeature/timeline/popularity/196"
  },
  "word-break-break-word": {},
  "word-spacing": {},
  "writing-mode": {},
  "writing-mode-svg-values": {},
  "writingsuggestions": {
    "percentageOfPageLoad": 0.00209197,
    "chromeStatusUrl": "https://chromestatus.com/metrics/webfeature/timeline/popularity/262"
  },
  "xhr": {},
  "xml-serializer": {},
  "xpath": {},
  "xslt": {},
  "z-index": {},
  "zoom": {},
  "zstd": {
    "percentageOfPageLoad": 0.38297365,
    "chromeStatusUrl": "https://chromestatus.com/metrics/webfeature/timeline/popularity/291"
  }
}